blaxbird/__init__.py
blaxbird/experimental.py
blaxbird/_src/__init__.py
blaxbird/_src/checkpointer.py
blaxbird/_src/test_blaxbird.py
blaxbird/_src/trainer.py
blaxbird/_src/experimental/__init__.py
blaxbird/_src/experimental/edm.py
blaxbird/_src/experimental/rfm.py
blaxbird/_src/experimental/samplers.py
blaxbird/_src/experimental/nn/__init__.py
blaxbird/_src/experimental/nn/dit.py
blaxbird/_src/experimental/nn/embedding.py
blaxbird/_src/experimental/nn/mlp.py
blaxbird-0.1.0.dist-info/licenses/LICENSE
blaxbird-0.1.0.dist-info/METADATA
blaxbird-0.1.0.dist-info/WHEEL
blaxbird-0.1.0.dist-info/top_level.txt
blaxbird-0.1.0.dist-info/RECORD
