Metadata-Version: 2.4
Name: blaxbird
Version: 0.1.0
Summary: A high-level API for building and training Flax NNX models.
Author-email: Simon Dirmeier <simd@mailbox.org>
License: 
Project-URL: Homepage, https://github.com/dirmeier/blaxbird
Classifier: Development Status :: 1 - Planning
Classifier: Intended Audience :: Science/Research
Classifier: Programming Language :: Python :: 3
Classifier: Programming Language :: Python :: 3.10
Classifier: Programming Language :: Python :: 3.11
Classifier: Programming Language :: Python :: 3.12
Requires-Python: >=3.10
License-File: LICENSE
Requires-Dist: einops>=0.8.1
Requires-Dist: jax-ai-stack
Requires-Dist: ml-collections>=1.1.0
Provides-Extra: all
Dynamic: license-file
